MANIFEST.in
README.rst
setup.py
json_hyper_schema/__init__.py
json_hyper_schema/patch.py
json_hyper_schema/schema.py
json_hyper_schema/test.py
json_hyper_schema.egg-info/PKG-INFO
json_hyper_schema.egg-info/SOURCES.txt
json_hyper_schema.egg-info/dependency_links.txt
json_hyper_schema.egg-info/requires.txt
json_hyper_schema.egg-info/top_level.txt