Metadata-Version: 1.0
Name: json-hyper-schema
Version: 0.4
Summary: UNKNOWN
Home-page: UNKNOWN
Author: Ernst Odolphi
Author-email: ernst.odolphi@gmail.com
License: UNKNOWN
Platform: UNKNOWN
